<config>
    <init>
        <system>linux</system>
        <end_dir>/home/frost/Documents/raw_docs</end_dir>
        <sleep_time>5</sleep_time>

        <scan_dir>
            <dir>/home/frost/Downloads</dir>
        </scan_dir>

        <file_structure>
            <folder>
                <name>pdf</name>
                <ext>pdf</ext>
            </folder>
            <folder>
                <name>excel</name>
                <ext>xls</ext>
                <ext>xlsm</ext>
                <ext>xlsx</ext>
            </folder>
            <folder>
                <name>word</name>
                <ext>doc</ext>
                <ext>docx</ext>
                <ext>txt</ext>
            </folder>
            <folder>
                <name>power_point</name>
                <ext>ppt</ext>
            </folder>
            <folder>
                <!-- Any types placed in misc is a blacklist -->
                <name>misc</name>
            </folder>
        </file_structure>

    </init>
</config>